tensorflow_io_2.0_preview-0.7.0.dev1369.data/purelib/tensorflow_io/__init__.py
tensorflow_io_2.0_preview-0.7.0.dev1369.data/purelib/tensorflow_io/arrow/__init__.py
tensorflow_io_2.0_preview-0.7.0.dev1369.data/purelib/tensorflow_io/arrow/python/__init__.py
tensorflow_io_2.0_preview-0.7.0.dev1369.data/purelib/tensorflow_io/arrow/python/ops/__init__.py
tensorflow_io_2.0_preview-0.7.0.dev1369.data/purelib/tensorflow_io/arrow/python/ops/_arrow_ops.so
tensorflow_io_2.0_preview-0.7.0.dev1369.data/purelib/tensorflow_io/arrow/python/ops/arrow_dataset_ops.py
tensorflow_io_2.0_preview-0.7.0.dev1369.data/purelib/tensorflow_io/audio/__init__.py
tensorflow_io_2.0_preview-0.7.0.dev1369.data/purelib/tensorflow_io/audio/python/__init__.py
tensorflow_io_2.0_preview-0.7.0.dev1369.data/purelib/tensorflow_io/audio/python/ops/__init__.py
tensorflow_io_2.0_preview-0.7.0.dev1369.data/purelib/tensorflow_io/audio/python/ops/audio_ops.py
tensorflow_io_2.0_preview-0.7.0.dev1369.data/purelib/tensorflow_io/avro/__init__.py
tensorflow_io_2.0_preview-0.7.0.dev1369.data/purelib/tensorflow_io/avro/python/__init__.py
tensorflow_io_2.0_preview-0.7.0.dev1369.data/purelib/tensorflow_io/avro/python/ops/__init__.py
tensorflow_io_2.0_preview-0.7.0.dev1369.data/purelib/tensorflow_io/avro/python/ops/avro_ops.py
tensorflow_io_2.0_preview-0.7.0.dev1369.data/purelib/tensorflow_io/azure/__init__.py
tensorflow_io_2.0_preview-0.7.0.dev1369.data/purelib/tensorflow_io/azure/python/__init__.py
tensorflow_io_2.0_preview-0.7.0.dev1369.data/purelib/tensorflow_io/bigquery/__init__.py
tensorflow_io_2.0_preview-0.7.0.dev1369.data/purelib/tensorflow_io/bigquery/python/ops/_bigquery.so
tensorflow_io_2.0_preview-0.7.0.dev1369.data/purelib/tensorflow_io/bigtable/__init__.py
tensorflow_io_2.0_preview-0.7.0.dev1369.data/purelib/tensorflow_io/bigtable/python/__init__.py
tensorflow_io_2.0_preview-0.7.0.dev1369.data/purelib/tensorflow_io/bigtable/python/ops/__init__.py
tensorflow_io_2.0_preview-0.7.0.dev1369.dist-info/METADATA
tensorflow_io_2.0_preview-0.7.0.dev1369.dist-info/WHEEL
tensorflow_io_2.0_preview-0.7.0.dev1369.dist-info/top_level.txt
tensorflow_io_2.0_preview-0.7.0.dev1369.dist-info/RECORD
