Metadata-Version: 2.1
Name: tensorflow-io-2.0-preview
Version: 0.7.0.dev1369
Summary: TensorFlow IO
Home-page: UNKNOWN
Author: Google Inc.
Author-email: opensource@google.com
License: Apache 2.0
Keywords: tensorflow io machine learning
Platform: UNKNOWN
Classifier: Development Status :: 4 - Beta
Classifier: Intended Audience :: Developers
Classifier: Intended Audience :: Education
Classifier: Intended Audience :: Science/Research
Classifier: License :: OSI Approved :: Apache Software License
Classifier: Programming Language :: Python :: 2.7
Classifier: Programming Language :: Python :: 3.5
Classifier: Programming Language :: Python :: 3.6
Classifier: Topic :: Scientific/Engineering :: Mathematics
Classifier: Topic :: Software Development :: Libraries :: Python Modules
Classifier: Topic :: Software Development :: Libraries
Requires-Dist: tensorflow (==2.0.0b1)
